odoo/addons/graphql_demo/README.rst
odoo/addons/graphql_demo/__init__.py
odoo/addons/graphql_demo/__manifest__.py
odoo/addons/graphql_demo/schema.py
odoo/addons/graphql_demo/controllers/__init__.py
odoo/addons/graphql_demo/controllers/main.py
odoo/addons/graphql_demo/i18n/graphql_demo.pot
odoo/addons/graphql_demo/readme/DESCRIPTION.rst
odoo/addons/graphql_demo/readme/USAGE.rst
odoo/addons/graphql_demo/static/description/icon.png
odoo/addons/graphql_demo/static/description/index.html
odoo/addons/graphql_demo/tests/__init__.py
odoo/addons/graphql_demo/tests/test_controller.py
odoo/addons/graphql_demo/tests/test_graphene.py
odoo12_addon_graphql_demo-12.0.1.0.0.99.dev24.dist-info/METADATA
odoo12_addon_graphql_demo-12.0.1.0.0.99.dev24.dist-info/WHEEL
odoo12_addon_graphql_demo-12.0.1.0.0.99.dev24.dist-info/top_level.txt
odoo12_addon_graphql_demo-12.0.1.0.0.99.dev24.dist-info/RECORD
